{
  "$schema": "https://mintlify.com/docs.json",
  "name": "Hafiportrait Platform",
  "description": "Platform manajemen galeri foto pernikahan dan event",
  "theme": "mint",
  "colors": {
    "primary": "#0f172a",
    "light": "#334155",
    "dark": "#0f172a"
  },
  "navbar": {
    "links": [
      {
        "label": "GitHub",
        "href": "https://github.com/ylxai/hafispace",
        "type": "github"
      }
    ],
    "primary": {
      "type": "button",
      "label": "Dashboard",
      "href": "https://hafiportrait.com/admin"
    }
  },
  "navigation": {
    "groups": [
      {
        "group": "Memulai",
        "pages": [
          "introduction",
          "quickstart",
          "architecture"
        ]
      },
      {
        "group": "Panduan",
        "pages": [
          "guides/database",
          "guides/authentication",
          "guides/cloudinary",
          "guides/deployment"
        ]
      },
      {
        "group": "API Reference",
        "pages": [
          "api/overview",
          "api/health",
          "api/public/gallery",
          "api/public/booking",
          "api/public/invoice",
          "api/admin/bookings",
          "api/admin/clients",
          "api/admin/galleries",
          "api/admin/metrics"
        ]
      }
    ]
  },
  "footer": {
    "socials": {
      "github": "https://github.com/ylxai/hafispace"
    }
  },
  "seo": {
    "indexing": "all"
  }
}
